{"cameraMode":{"drawMode":0,"name":"Shaded","section":"Shading Mode"},"sceneLighting":true,"audioPlay":false,"sceneViewState":{"m_AlwaysRefresh":false,"showFog":true,"showSkybox":true,"showFlares":true,"showImageEffects":true,"showParticleSystems":true,"showVisualEffectGraphs":true,"m_FxEnabled":true},"in2DMode":false,"pivot":{"x":0.2970874607563019,"y":5.284526824951172,"z":-10.705859184265137},"rotation":{"x":-0.21159107983112336,"y":-0.10737749189138413,"z":0.02336244471371174,"w":-0.9712042808532715},"size":0.8660253882408142,"orthographic":false}