{"cameraMode":{"drawMode":0,"name":"Shaded","section":"Shading Mode"},"sceneLighting":true,"audioPlay":false,"sceneViewState":{"m_AlwaysRefresh":false,"showFog":true,"showSkybox":true,"showFlares":true,"showImageEffects":true,"showParticleSystems":true,"showVisualEffectGraphs":true,"m_FxEnabled":true},"in2DMode":false,"pivot":{"x":1.4448996782302857,"y":0.01662459969520569,"z":-2.6643576622009279},"rotation":{"x":0.07041584700345993,"y":-0.02304825186729431,"z":-0.0016617417568340898,"w":-0.9972924590110779},"size":0.8660253882408142,"orthographic":false}